<?xml version="1.0" encoding="UTF-8"?>
<!DOCTYPE suite SYSTEM "http://testng.org/testng-1.0.dtd">
<suite name="All Test Suite" parallel="methods" thread-count="2">
    <test verbose="2" preserve-order="true"
          name="/home/cuongnb/code/autotest/selenium-testng/src/main/test/com/autotest/ParallelMethodTest.java">
        <classes>
            <class name="com.autotest.ParallelMethodTest">
                <methods>
                    <include name="testMethodsOne"/>
                    <include name="testMethodsTwo"/>
                </methods>
            </class>
        </classes>
    </test>
</suite>